README.rst
setup.py
spendtime/__init__.py
spendtime/commands.py
spendtime/spendtime.py
spendtime.egg-info/PKG-INFO
spendtime.egg-info/SOURCES.txt
spendtime.egg-info/dependency_links.txt
spendtime.egg-info/entry_points.txt
spendtime.egg-info/not-zip-safe
spendtime.egg-info/requires.txt
spendtime.egg-info/top_level.txt