Metadata-Version: 1.1
Name: spendtime
Version: 0.1.1
Summary: Simple timetracking tool for the terminal
Home-page: https://github.com/morngrar/spendtime
Author: Svein-Kåre Bjørnsen
Author-email: sveinkare@gmail.com
License: GPL
Platform: UNKNOWN
Classifier: Development Status :: 4 - Beta
Classifier: Intended Audience :: End Users/Desktop
Classifier: License :: OSI Approved :: GNU General Public License v3 (GPLv3)
Classifier: Programming Language :: Python :: 3
Classifier: Topic :: Utilities
